{
    "title": "Assemble",
    "snippet": "Bringing urban elements together to form cohesive spaces",
    "description": "Assembly in urban planning is about creating harmony by bringing diverse urban elements together. This process ensures all parts of the city work cohesively to serve the needs of its inhabitants.",
    "imageLinks": [
      "https://picsum.photos/300/200?random=10",
      "https://picsum.photos/300/200?random=49",
      "https://picsum.photos/300/200?random=50"
    ],
    "literature": [
      "The Architecture of Community by Leon Krier",
      "Community and Privacy by Serge Chermayeff",
      "The City as an Assembly by Terry Williamson"
    ]
  }
  