{
    "title": "Stakeholders",
    "snippet": "Identifying and including key urban influencers",
    "description": "Stakeholders in urban planning are individuals or groups with a vested interest in urban projects. Addressing their needs and concerns promotes a balanced and inclusive development process.",
    "imageLinks": [
      "https://picsum.photos/300/200?random=28",
      "https://picsum.photos/300/200?random=83",
      "https://picsum.photos/300/200?random=84"
    ],
    "literature": [
      "Stakeholder Engagement by Amy B. Voegtle",
      "The Social Life of Small Urban Spaces by William H. Whyte",
      "Collaborative Planning by Patsy Healey"
    ]
  }
  